{
  "element": "WATER",
  "get_from": "Unknown Scroll, Social Summon, Secret Dungeon, Magic Shop",
  "good_for": [
    "fusion or food"
  ],
  "grade": "\u2605\u2605\u2605",
  "grade_num": 3,
  "links": {
    "DARK": "//summonerswar.co/dark-imp-garok/",
    "FIRE": "//summonerswar.co/fire-imp-cogma/",
    "IMAGE_AWAKE": "https://43ch47qsavx2jcvnr30057vk-wpengine.netdna-ssl.com/wp-content/uploads/2016/11/Fynn_Icon.png",
    "IMAGE_SLEEPY": "https://43ch47qsavx2jcvnr30057vk-wpengine.netdna-ssl.com/wp-content/uploads/2016/11/Imp_Water_Icon.png",
    "LIGHT": "//summonerswar.co/light-imp-taru/",
    "WATER": "//summonerswar.co/water-imp-fynn/",
    "WIND": "//summonerswar.co/wind-imp-ralphy/"
  },
  "mon_type": "Attack",
  "name_awaken": "Fynn",
  "name_full": "Water Imp (Fynn)",
  "name_sleepy": "Imp",
  "ratings": {
    "FOOD": 37.0,
    "KEEP_IT": 41.0,
    "MEH": 16.0,
    "THE_BEST": 7.0
  },
  "score_total": 4.1,
  "score_user": 6.0,
  "skillup_info": "Don\u2019t bother skilling up, feed it to Taru (Light Imp) instead",
  "when_awaken": "New Skill: [Violent Stab]"
}